README.md
setup.py
src/polybar_vikunja/__init__.py
src/polybar_vikunja/client.py
src/polybar_vikunja/config_helper.py
src/polybar_vikunja/popups.py
src/polybar_vikunja.egg-info/PKG-INFO
src/polybar_vikunja.egg-info/SOURCES.txt
src/polybar_vikunja.egg-info/dependency_links.txt
src/polybar_vikunja.egg-info/entry_points.txt
src/polybar_vikunja.egg-info/requires.txt
src/polybar_vikunja.egg-info/top_level.txt