Metadata-Version: 2.1
Name: polybar-vikunja
Version: 0.1.2
Summary: Vikunja plugin for Polybar
Home-page: https://github.com/conor-f/polybar-vikunja
License: UNKNOWN
Platform: UNKNOWN
Requires-Python: >=3.6
